influx_alert/__init__.py
influx_alert/client.py
influx_alert/endpoint.py
influx_alert/influx_alert.py
influx_alert/endpoints/__init__.py
influx_alert/endpoints/common.py
influx_alert/endpoints/extensions.py
influx_alert/endpoints/network.py
influx_alert/endpoints/vmware.py
InfluxAlert-0.1.2.dist-info/LICENSE
InfluxAlert-0.1.2.dist-info/METADATA
InfluxAlert-0.1.2.dist-info/WHEEL
InfluxAlert-0.1.2.dist-info/top_level.txt
InfluxAlert-0.1.2.dist-info/RECORD
