Metadata-Version: 2.1
Name: InfluxAlert
Version: 0.1.2
Summary: influx alert
Home-page: https://github.com/houm01/InfluxAlert
License-File: LICENSE
